chunk_metadata_adapter/__init__.py
chunk_metadata_adapter/ast.py
chunk_metadata_adapter/ast_nodes.py
chunk_metadata_adapter/ast_optimizer.py
chunk_metadata_adapter/chunk_query.py
chunk_metadata_adapter/complexity_analyzer.py
chunk_metadata_adapter/data_types.py
chunk_metadata_adapter/examples_module.py
chunk_metadata_adapter/filter_executor.py
chunk_metadata_adapter/filter_grammar.py
chunk_metadata_adapter/filter_parser.py
chunk_metadata_adapter/hybrid_search.py
chunk_metadata_adapter/metadata_builder.py
chunk_metadata_adapter/performance_analyzer.py
chunk_metadata_adapter/query_business_examples.py
chunk_metadata_adapter/query_examples.py
chunk_metadata_adapter/query_serialization_examples.py
chunk_metadata_adapter/query_validator.py
chunk_metadata_adapter/search_response.py
chunk_metadata_adapter/security_validator.py
chunk_metadata_adapter/semantic_chunk.py
chunk_metadata_adapter/utils.py
chunk_metadata_adapter/ast/__init__.py
chunk_metadata_adapter/ast/factory.py
chunk_metadata_adapter/ast/nodes.py
chunk_metadata_adapter/ast/parameterization.py
chunk_metadata_adapter/ast/serialization.py
chunk_metadata_adapter/ast/visitors.py
chunk_metadata_adapter/examples/__init__.py
chunk_metadata_adapter/examples/api_integration_examples.py
chunk_metadata_adapter/examples/ast_basic_usage.py
chunk_metadata_adapter/examples/ast_json_serialization_demo.py
chunk_metadata_adapter/examples/ast_parameterization_demo.py
chunk_metadata_adapter/examples/ast_visitor_pattern_usage.py
chunk_metadata_adapter/examples/bm25_search_examples.py
chunk_metadata_adapter/examples/bm25_tokens_example.py
chunk_metadata_adapter/examples/bm25_usage_examples.py
chunk_metadata_adapter/examples/chunk_query_integration_demo.py
chunk_metadata_adapter/examples/filter_executor_usage.py
chunk_metadata_adapter/examples/filter_parser_total_chunks_example.py
chunk_metadata_adapter/examples/metrics_demo.py
chunk_metadata_adapter-3.3.4.dist-info/METADATA
chunk_metadata_adapter-3.3.4.dist-info/WHEEL
chunk_metadata_adapter-3.3.4.dist-info/top_level.txt
chunk_metadata_adapter-3.3.4.dist-info/RECORD
