Metadata-Version: 2.4
Name: chunk_metadata_adapter
Version: 3.3.4
Summary: Reusable metadata builder for chunk-based systems with BM25 tokens support
Author: Vasiliy zdanovskiy vasilyvz@gmail.com
License: MIT
Project-URL: Homepage, https://github.com/yourusername/chunk_metadata_adapter
Project-URL: Bug Tracker, https://github.com/yourusername/chunk_metadata_adapter/issues
Classifier: Programming Language :: Python :: 3
Classifier: Programming Language :: Python :: 3.8
Classifier: Programming Language :: Python :: 3.9
Classifier: Programming Language :: Python :: 3.10
Classifier: Operating System :: OS Independent
Requires-Python: >=3.8
Requires-Dist: pydantic>=2.0.0
Requires-Dist: lark>=1.1.5
Provides-Extra: dev
Requires-Dist: hypothesis>=6.0.0; extra == "dev"
Requires-Dist: pytest>=7.0.0; extra == "dev"
Requires-Dist: pytest-cov>=4.0.0; extra == "dev"
Requires-Dist: black>=23.0.0; extra == "dev"
Requires-Dist: isort>=5.0.0; extra == "dev"
Requires-Dist: mypy>=1.0.0; extra == "dev"
